setup.cfg
setup.py
django_debug_html_store/__init__.py
django_debug_html_store/middleware.py
django_debug_html_store/urls.py
django_debug_html_store/views.py
django_debug_html_store.egg-info/PKG-INFO
django_debug_html_store.egg-info/SOURCES.txt
django_debug_html_store.egg-info/dependency_links.txt
django_debug_html_store.egg-info/top_level.txt