Metadata-Version: 1.0
Name: django-debug-html-store
Version: 0.0.2
Summary: `django_debug_html_store` is django debug tool.
Home-page: http://github.com/salexkidd/django-debug_html_store
Author: salexkidd (salexkidd@gmail.com)
Author-email: salexkidd@gmail.com
License: MIT License
Keywords: django,debug,response
Platform: UNKNOWN
Classifier: Development Status :: 1 - Planning
Classifier: Topic :: Software Development :: Debuggers
Classifier: License :: OSI Approved :: MIT License
Classifier: Programming Language :: Python
Classifier: Framework :: Django
